{
  "definitionId": "fanout-demo",
  "root": {
    "type": "Elsa.Flowchart",
    "activities": [
      {
        "id": "start",
        "type": "Elsa.Start"
      },
      {
        "id": "branch1",
        "type": "Elsa.WriteLine",
        "text": "Branch 1"
      },
      {
        "id": "branch2",
        "type": "Elsa.WriteLine",
        "text": "Branch 2"
      },
      {
        "id": "join",
        "type": "Elsa.Join",
        "mode": "WaitAll"
      },
      {
        "id": "end",
        "type": "Elsa.WriteLine",
        "text": "All branches complete"
      }
    ],
    "connections": [
      {
        "source": "start",
        "target": "branch1"
      },
      {
        "source": "start",
        "target": "branch2"
      },
      {
        "source": "branch1",
        "target": "join"
      },
      {
        "source": "branch2",
        "target": "join"
      },
      {
        "source": "join",
        "target": "end"
      }
    ]
  }
}